cefim/__init__.py
cefim/data_api.py
cefim-0.5.dist-info/licenses/LICENSE
cefim-0.5.dist-info/METADATA
cefim-0.5.dist-info/WHEEL
cefim-0.5.dist-info/top_level.txt
cefim-0.5.dist-info/RECORD
