Metadata-Version: 2.4
Name: cefim
Version: 0.5
Summary: Repository of Insper's Finance and Macro Unit
Author: Insper's Finance Unit
Maintainer: Insper's Finance Unit
Maintainer-email: cefim@insper.edu.br
Keywords: finance,financial data,macroeconomics,quant finance,quantitative finance
License-File: LICENSE
Requires-Dist: pandas
Requires-Dist: requests
Dynamic: author
Dynamic: description
Dynamic: description-content-type
Dynamic: keywords
Dynamic: license-file
Dynamic: maintainer
Dynamic: maintainer-email
Dynamic: requires-dist
Dynamic: summary
